mecrab-0.1.2.dist-info/METADATA
mecrab-0.1.2.dist-info/WHEEL
mecrab/__init__.py
mecrab/mecrab.cpython-314-darwin.so
mecrab/mecrab.pyi
mecrab/py.typed
mecrab-0.1.2.dist-info/RECORD
