Metadata-Version: 2.4
Name: mecrab
Version: 0.1.2
Classifier: Development Status :: 4 - Beta
Classifier: Intended Audience :: Developers
Classifier: Intended Audience :: Science/Research
Classifier: License :: OSI Approved :: MIT License
Classifier: License :: OSI Approved :: Apache Software License
Classifier: Operating System :: POSIX :: Linux
Classifier: Operating System :: MacOS
Classifier: Operating System :: Microsoft :: Windows
Classifier: Programming Language :: Python :: 3
Classifier: Programming Language :: Python :: 3.9
Classifier: Programming Language :: Python :: 3.10
Classifier: Programming Language :: Python :: 3.11
Classifier: Programming Language :: Python :: 3.12
Classifier: Programming Language :: Rust
Classifier: Topic :: Text Processing :: Linguistic
Classifier: Topic :: Scientific/Engineering :: Artificial Intelligence
Requires-Dist: pytest>=7.0 ; extra == 'dev'
Requires-Dist: pytest-benchmark>=4.0 ; extra == 'dev'
Provides-Extra: dev
Summary: High-performance morphological analyzer compatible with MeCab
Keywords: nlp,morphological-analysis,mecab,japanese,tokenizer
Author: COOLJAPAN OU (Team KitaSan)
License: MIT OR Apache-2.0
Requires-Python: >=3.9
Project-URL: Homepage, https://github.com/cool-japan/mecrab
Project-URL: Repository, https://github.com/cool-japan/mecrab
Project-URL: Documentation, https://docs.rs/mecrab
